[
    {
        "name": "Star Sports 1",
        "id": "star1in",
        "logo": "https://cdn.jsdelivr.net/gh/HelloPeopleTv4you/tv-logo@refs/heads/main/crichd2-runded/16-by-xfireflix.png",
        "link": "https://m7.merichunidya.com:999/hls/star1in.m3u8?md5=Kri5Y7L5zbwCypdqzz0FzQ&expires=1746054901",
        "referer": "https://stylisheleg4nt.com",
        "origin": "https://stylisheleg4nt.com"
    },
    {
        "name": "Star Sports 1 Hindi",
        "id": "starhindi",
        "logo": "https://cdn.jsdelivr.net/gh/HelloPeopleTv4you/tv-logo@refs/heads/main/crichd2-runded/1-by-xfireflix.png",
        "link": "https://m5.merichunidya.com:999/hls/starhindi.m3u8?md5=Qp9IgbdBWjFKNTcdDAzXJw&expires=1746054902",
        "referer": "https://stylisheleg4nt.com",
        "origin": "https://stylisheleg4nt.com"
    },
    {
        "name": "PTV Sports",
        "id": "ptvpk",
        "logo": "https://cdn.jsdelivr.net/gh/HelloPeopleTv4you/tv-logo@refs/heads/main/crichd2-runded/20-by-xfireflix.png",
        "link": "https://m6.merichunidya.com:999/hls/ptvpk.m3u8?md5=UX3IkMjNKeo2qt_wpfb0Tw&expires=1746054902",
        "referer": "https://stylisheleg4nt.com",
        "origin": "https://stylisheleg4nt.com"
    },
    {
        "name": "Willow HD",
        "id": "willowusa",
        "logo": "https://cdn.jsdelivr.net/gh/HelloPeopleTv4you/tv-logo@refs/heads/main/crichd2-runded/38-by-xfireflix.png",
        "link": "https://m6.merichunidya.com:999/hls/willowusa.m3u8?md5=rZJgaT33hLEeNzTYzjEUgg&expires=1746054902",
        "referer": "https://stylisheleg4nt.com",
        "origin": "https://stylisheleg4nt.com"
    },
    {
        "name": "Willow HD 2",
        "id": "willowextra",
        "logo": "https://cdn.jsdelivr.net/gh/HelloPeopleTv4you/tv-logo@refs/heads/main/crichd2-runded/8-by-xfireflix.png",
        "link": "https://m7.merichunidya.com:999/hls/willowextra.m3u8?md5=p2dSBEH0H_VUAAqNY2nFHQ&expires=1746054902",
        "referer": "https://stylisheleg4nt.com",
        "origin": "https://stylisheleg4nt.com"
    },
    {
        "name": "Ten Sports",
        "id": "tenspk",
        "logo": "https://cdn.jsdelivr.net/gh/HelloPeopleTv4you/tv-logo@refs/heads/main/crichd2-runded/10-by-xfireflix.png",
        "link": "https://m6.merichunidya.com:999/hls/tenspk.m3u8?md5=iahuiM9lVgWcTdH4SPVs3Q&expires=1746054902",
        "referer": "https://stylisheleg4nt.com",
        "origin": "https://stylisheleg4nt.com"
    },
    {
        "name": "A Sports HD",
        "id": "asportshd",
        "logo": "https://cdn.jsdelivr.net/gh/HelloPeopleTv4you/tv-logo@refs/heads/main/crichd2-runded/12-by-xfireflix.png",
        "link": "https://m7.merichunidya.com:999/hls/asportshd.m3u8?md5=DCCektGl9CP0K3GjoeGnKw&expires=1746054902",
        "referer": "https://stylisheleg4nt.com",
        "origin": "https://stylisheleg4nt.com"
    },
    {
        "name": "Sky Sports Cricket",
        "id": "skyscric",
        "logo": "https://cdn.jsdelivr.net/gh/HelloPeopleTv4you/tv-logo@refs/heads/main/crichd2-runded/9-by-xfireflix.png",
        "link": "https://m5.merichunidya.com:999/hls/skyscric.m3u8?md5=prIUNF1PPntTb5on4L-fkA&expires=1746054902",
        "referer": "https://stylisheleg4nt.com",
        "origin": "https://stylisheleg4nt.com"
    },
    {
        "name": "Sky Sports Main Event",
        "id": "skysme",
        "logo": "https://cdn.jsdelivr.net/gh/HelloPeopleTv4you/tv-logo@refs/heads/main/crichd2-runded/18-by-xfireflix.png",
        "link": "https://m7.merichunidya.com:999/hls/skysme.m3u8?md5=AbE4pjWFpLr2lbbpd8H_yg&expires=1746054902",
        "referer": "https://stylisheleg4nt.com",
        "origin": "https://stylisheleg4nt.com"
    },
    {
        "name": "TNT 1",
        "id": "bbtsp1",
        "logo": "https://cdn.jsdelivr.net/gh/HelloPeopleTv4you/tv-logo@refs/heads/main/crichd2-runded/tnt.png",
        "link": "https://m5.merichunidya.com:999/hls/bbtsp1.m3u8?md5=QsTQoZglDsQ9qGoWi0-qpg&expires=1746054902",
        "referer": "https://stylisheleg4nt.com",
        "origin": "https://stylisheleg4nt.com"
    },
    {
        "name": "TNT 2",
        "id": "bbtsp2",
        "logo": "https://cdn.jsdelivr.net/gh/HelloPeopleTv4you/tv-logo@refs/heads/main/crichd2-runded/tnt.png",
        "link": "https://m7.merichunidya.com:999/hls/bbtsp2.m3u8?md5=W7ij6uXdLaueUGZydsxVBw&expires=1746054902",
        "referer": "https://stylisheleg4nt.com",
        "origin": "https://stylisheleg4nt.com"
    },
    {
        "name": "TNT 3",
        "id": "bbtsp3",
        "logo": "https://cdn.jsdelivr.net/gh/HelloPeopleTv4you/tv-logo@refs/heads/main/crichd2-runded/tnt.png",
        "link": "https://m6.merichunidya.com:999/hls/bbtsp3.m3u8?md5=6WQcPnJv6gmKidKcVtQkGA&expires=1746054902",
        "referer": "https://stylisheleg4nt.com",
        "origin": "https://stylisheleg4nt.com"
    },
    {
        "name": "TNT 4",
        "id": "bbtespn",
        "logo": "https://cdn.jsdelivr.net/gh/HelloPeopleTv4you/tv-logo@refs/heads/main/crichd2-runded/tnt.png",
        "link": "https://m5.merichunidya.com:999/hls/bbtespn.m3u8?md5=mD9NON61aFwm9sejvD9NOw&expires=1746054902",
        "referer": "https://stylisheleg4nt.com",
        "origin": "https://stylisheleg4nt.com"
    },
    {
        "name": "Sky Sports 1",
        "id": "sky1nz",
        "logo": "https://cdn.jsdelivr.net/gh/HelloPeopleTv4you/tv-logo@refs/heads/main/crichd2-runded/56-by-xfireflix.png",
        "link": "https://m5.merichunidya.com:999/hls/sky1nz.m3u8?md5=EXYF4rU3TDjltfUCnKxU6Q&expires=1746054902",
        "referer": "https://stylisheleg4nt.com",
        "origin": "https://stylisheleg4nt.com"
    },
    {
        "name": "Sky Sports 2",
        "id": "sky2nz",
        "logo": "https://cdn.jsdelivr.net/gh/HelloPeopleTv4you/tv-logo@refs/heads/main/crichd2-runded/56-by-xfireflix.png",
        "link": "https://m6.merichunidya.com:999/hls/sky2nz.m3u8?md5=i7EKjtXrCLn3WE-K8sguYQ&expires=1746054902",
        "referer": "https://stylisheleg4nt.com",
        "origin": "https://stylisheleg4nt.com"
    },
    {
        "name": "Sky Sports 3",
        "id": "sky3nz",
        "logo": "https://cdn.jsdelivr.net/gh/HelloPeopleTv4you/tv-logo@refs/heads/main/crichd2-runded/56-by-xfireflix.png",
        "link": "https://m7.merichunidya.com:999/hls/sky3nz.m3u8?md5=bv09FtPJFcFAKTRdhmRNTQ&expires=1746054903",
        "referer": "https://stylisheleg4nt.com",
        "origin": "https://stylisheleg4nt.com"
    },
    {
        "name": "Sky Sports 4",
        "id": "sky4nz",
        "logo": "https://cdn.jsdelivr.net/gh/HelloPeopleTv4you/tv-logo@refs/heads/main/crichd2-runded/56-by-xfireflix.png",
        "link": "https://m5.merichunidya.com:999/hls/sky4nz.m3u8?md5=V1zXF0Y-A86WiSe3P0dd6Q&expires=1746054903",
        "referer": "https://stylisheleg4nt.com",
        "origin": "https://stylisheleg4nt.com"
    },
    {
        "name": "Sky Sports 5",
        "id": "sky5nz",
        "logo": "https://cdn.jsdelivr.net/gh/HelloPeopleTv4you/tv-logo@refs/heads/main/crichd2-runded/56-by-xfireflix.png",
        "link": "https://m7.merichunidya.com:999/hls/sky5nz.m3u8?md5=hHw5v9t-KkosXSqiioD-Pg&expires=1746054903",
        "referer": "https://stylisheleg4nt.com",
        "origin": "https://stylisheleg4nt.com"
    },
    {
        "name": "Sky Sports 6",
        "id": "sky6nz",
        "logo": "https://cdn.jsdelivr.net/gh/HelloPeopleTv4you/tv-logo@refs/heads/main/crichd2-runded/56-by-xfireflix.png",
        "link": "https://m5.merichunidya.com:999/hls/sky6nz.m3u8?md5=Btxwj-8-NBD0kZgaliocjw&expires=1746054903",
        "referer": "https://stylisheleg4nt.com",
        "origin": "https://stylisheleg4nt.com"
    },
    {
        "name": "Sky Sports 7",
        "id": "sky7nz",
        "logo": "https://cdn.jsdelivr.net/gh/HelloPeopleTv4you/tv-logo@refs/heads/main/crichd2-runded/56-by-xfireflix.png",
        "link": "https://m6.merichunidya.com:999/hls/sky7nz.m3u8?md5=v9KbUlBSJ_WxTQy_Pc6N7g&expires=1746054903",
        "referer": "https://stylisheleg4nt.com",
        "origin": "https://stylisheleg4nt.com"
    },
    {
        "name": "Sky Sports 8",
        "id": "sky8nz",
        "logo": "https://cdn.jsdelivr.net/gh/HelloPeopleTv4you/tv-logo@refs/heads/main/crichd2-runded/56-by-xfireflix.png",
        "link": "https://m6.merichunidya.com:999/hls/sky8nz.m3u8?md5=sCtxo8JeWRzYzY3QZM2nug&expires=1746054903",
        "referer": "https://stylisheleg4nt.com",
        "origin": "https://stylisheleg4nt.com"
    },
    {
        "name": "Sky Sports 9",
        "id": "sky9nz",
        "logo": "https://cdn.jsdelivr.net/gh/HelloPeopleTv4you/tv-logo@refs/heads/main/crichd2-runded/56-by-xfireflix.png",
        "link": "https://m7.merichunidya.com:999/hls/sky9nz.m3u8?md5=M0VBjq3l8QJJeOmB7-8TKQ&expires=1746054903",
        "referer": "https://stylisheleg4nt.com",
        "origin": "https://stylisheleg4nt.com"
    },
    {
        "name": "Sky Cinema",
        "id": "skysme",
        "logo": "https://cdn.jsdelivr.net/gh/HelloPeopleTv4you/tv-logo@refs/heads/main/crichd2-runded/skycinema.png",
        "link": "https://m6.merichunidya.com:999/hls/skysme.m3u8?md5=o5RUNiRXEcPLLblOwtBXRg&expires=1746054903",
        "referer": "https://stylisheleg4nt.com",
        "origin": "https://stylisheleg4nt.com"
    },
    {
        "name": "Sky Sports Action",
        "id": "skysact",
        "logo": "https://cdn.jsdelivr.net/gh/HelloPeopleTv4you/tv-logo@refs/heads/main/crichd2-runded/1745007829332.png",
        "link": "https://m7.merichunidya.com:999/hls/skysact.m3u8?md5=tSudVFgCeUcNh88V9PLLZg&expires=1746054903",
        "referer": "https://stylisheleg4nt.com",
        "origin": "https://stylisheleg4nt.com"
    },
    {
        "name": "Sky Sports Golf",
        "id": "skysgol",
        "logo": "https://cdn.jsdelivr.net/gh/HelloPeopleTv4you/tv-logo@refs/heads/main/crichd2-runded/1745008055327.png",
        "link": "https://m5.merichunidya.com:999/hls/skysgol.m3u8?md5=mcy0EcltsJ_9gScskL9naQ&expires=1746054903",
        "referer": "https://stylisheleg4nt.com",
        "origin": "https://stylisheleg4nt.com"
    },
    {
        "name": "Sky Sports Premier League",
        "id": "skysprem",
        "logo": "https://cdn.jsdelivr.net/gh/HelloPeopleTv4you/tv-logo@refs/heads/main/crichd2-runded/43-by-xfireflix.png",
        "link": "https://m6.merichunidya.com:999/hls/skysprem.m3u8?md5=5XnYwy3cZEVfhAViRsACkQ&expires=1746054903",
        "referer": "https://stylisheleg4nt.com",
        "origin": "https://stylisheleg4nt.com"
    },
    {
        "name": "Sky Sports Football",
        "id": "skysfott",
        "logo": "https://cdn.jsdelivr.net/gh/HelloPeopleTv4you/tv-logo@refs/heads/main/crichd2-runded/44-by-xfireflix.png",
        "link": "https://m6.merichunidya.com:999/hls/skysfott.m3u8?md5=n30pi1BY2l0b_2cEhslTYQ&expires=1746054903",
        "referer": "https://stylisheleg4nt.com",
        "origin": "https://stylisheleg4nt.com"
    },
    {
        "name": "Sky Sports Plus",
        "logo": "https://cdn.jsdelivr.net/gh/HelloPeopleTv4you/tv-logo@refs/heads/main/crichd2-runded/1745008347584.png",
        "error": "Token not found or failed to fetch."
    },
    {
        "name": "Sky Sports F1",
        "id": "skysfor1",
        "logo": "https://cdn.jsdelivr.net/gh/HelloPeopleTv4you/tv-logo@refs/heads/main/crichd2-runded/1745008468637.png",
        "link": "https://m7.merichunidya.com:999/hls/skysfor1.m3u8?md5=jyC5It4s75_ieMLjC458WQ&expires=1746054904",
        "referer": "https://stylisheleg4nt.com",
        "origin": "https://stylisheleg4nt.com"
    },
    {
        "name": "LaLiGA",
        "id": "laligauk",
        "logo": "https://cdn.jsdelivr.net/gh/HelloPeopleTv4you/tv-logo@refs/heads/main/crichd2-runded/19-by-xfireflix.png",
        "link": "https://m6.merichunidya.com:999/hls/laligauk.m3u8?md5=xgETCp5j5cYa1f-Lx3iqkg&expires=1746054904",
        "referer": "https://stylisheleg4nt.com",
        "origin": "https://stylisheleg4nt.com"
    },
    {
        "name": "Premier Sports 1",
        "id": "premieruk",
        "logo": "https://cdn.jsdelivr.net/gh/HelloPeopleTv4you/tv-logo@refs/heads/main/crichd2-runded/31-by-xfireflix.png",
        "link": "https://m6.merichunidya.com:999/hls/premieruk.m3u8?md5=-l3Mw0LNKayy2RdkMieKsw&expires=1746054904",
        "referer": "https://stylisheleg4nt.com",
        "origin": "https://stylisheleg4nt.com"
    },
    {
        "name": "Premier Sports 2",
        "id": "hdchnl2",
        "logo": "https://cdn.jsdelivr.net/gh/HelloPeopleTv4you/tv-logo@refs/heads/main/crichd2-runded/31-by-xfireflix.png",
        "link": "https://m5.merichunidya.com:999/hls/hdchnl2.m3u8?md5=TgzeE_UvqNUid9bZUMTFkQ&expires=1746054904",
        "referer": "https://stylisheleg4nt.com",
        "origin": "https://stylisheleg4nt.com"
    },
    {
        "name": "Super Football",
        "id": "superfotball",
        "logo": "https://cdn.jsdelivr.net/gh/HelloPeopleTv4you/tv-logo@refs/heads/main/crichd2-runded/34-by-xfireflix.png",
        "link": "https://m5.merichunidya.com:999/hls/superfotball.m3u8?md5=qF4vFWv-YwZUW3_wZ7Mrwg&expires=1746054904",
        "referer": "https://stylisheleg4nt.com",
        "origin": "https://stylisheleg4nt.com"
    },
    {
        "name": "Super Premier League",
        "id": "superpremier",
        "logo": "https://cdn.jsdelivr.net/gh/HelloPeopleTv4you/tv-logo@refs/heads/main/crichd2-runded/1745008781606.png",
        "link": "https://m5.merichunidya.com:999/hls/superpremier.m3u8?md5=ghY1psdoX3Gw-h5vWlLkyQ&expires=1746054904",
        "referer": "https://stylisheleg4nt.com",
        "origin": "https://stylisheleg4nt.com"
    },
    {
        "name": "Astro Cricket",
        "id": "fox501",
        "logo": "https://cdn.jsdelivr.net/gh/HelloPeopleTv4you/tv-logo@refs/heads/main/crichd2-runded/1745008895589.png",
        "link": "https://m5.merichunidya.com:999/hls/fox501.m3u8?md5=vaGpD_-zWs2igy0mFfS1qQ&expires=1746054904",
        "referer": "https://stylisheleg4nt.com",
        "origin": "https://stylisheleg4nt.com"
    },
    {
        "name": "ESPN 1",
        "id": "espnusa",
        "logo": "https://cdn.jsdelivr.net/gh/HelloPeopleTv4you/tv-logo@refs/heads/main/crichd2-runded/17-by-xfireflix.png",
        "link": "https://m6.merichunidya.com:999/hls/espnusa.m3u8?md5=5kctIbv41JuD-Jdz2IELyQ&expires=1746054904",
        "referer": "https://stylisheleg4nt.com",
        "origin": "https://stylisheleg4nt.com"
    },
    {
        "name": "ESPN 2",
        "id": "espn2",
        "logo": "https://cdn.jsdelivr.net/gh/HelloPeopleTv4you/tv-logo@refs/heads/main/crichd2-runded/17-by-xfireflix.png",
        "link": "https://m5.merichunidya.com:999/hls/espn2.m3u8?md5=VttL2C3aYr7kt4QQ8ZkGLQ&expires=1746054904",
        "referer": "https://stylisheleg4nt.com",
        "origin": "https://stylisheleg4nt.com"
    },
    {
        "name": "Sky Sports Arena",
        "logo": "https://cdn.jsdelivr.net/gh/HelloPeopleTv4you/tv-logo@refs/heads/main/crichd2-runded/1745007829327.png",
        "error": "Token not found or failed to fetch."
    },
    {
        "name": "Sky Sports Mix",
        "id": "skysmixx",
        "logo": "https://cdn.jsdelivr.net/gh/HelloPeopleTv4you/tv-logo@refs/heads/main/crichd2-runded/13-by-xfireflix.png",
        "link": "https://m5.merichunidya.com:999/hls/skysmixx.m3u8?md5=lll76h7wXjR00kdfxO5Vfw&expires=1746054904",
        "referer": "https://stylisheleg4nt.com",
        "origin": "https://stylisheleg4nt.com"
    },
    {
        "name": "Sky Sports Tennis",
        "id": "skystennis",
        "logo": "https://cdn.jsdelivr.net/gh/HelloPeopleTv4you/tv-logo@refs/heads/main/crichd2-runded/1745009085794.png",
        "link": "https://m6.merichunidya.com:999/hls/skystennis.m3u8?md5=dw_yxpzZOAg7Sn5gJJ1UKw&expires=1746054904",
        "referer": "https://stylisheleg4nt.com",
        "origin": "https://stylisheleg4nt.com"
    },
    {
        "name": "Fox Cricket 501 HD",
        "id": "fox501",
        "logo": "https://cdn.jsdelivr.net/gh/HelloPeopleTv4you/tv-logo@refs/heads/main/crichd2-runded/6-by-xfireflix.png",
        "link": "https://m5.merichunidya.com:999/hls/fox501.m3u8?md5=vaGpD_-zWs2igy0mFfS1qQ&expires=1746054904",
        "referer": "https://stylisheleg4nt.com",
        "origin": "https://stylisheleg4nt.com"
    }
]