[
    {
        "name": "Star Sports 1",
        "id": "star1in",
        "logo": "https://cdn.jsdelivr.net/gh/HelloPeopleTv4you/tv-logo@refs/heads/main/crichd2-runded/16-by-xfireflix.png",
        "link": "https://m1.merichunidya.com:999/hls/star1in.m3u8?md5=nNLCngJZtzMUMPfgCRBYuA&expires=1747430024",
        "referer": "https://stylisheleg4nt.com",
        "origin": "https://stylisheleg4nt.com"
    },
    {
        "name": "Star Sports 1 Hindi",
        "id": "starhindi",
        "logo": "https://cdn.jsdelivr.net/gh/HelloPeopleTv4you/tv-logo@refs/heads/main/crichd2-runded/1-by-xfireflix.png",
        "link": "https://m4.merichunidya.com:999/hls/starhindi.m3u8?md5=93n_DJa5z6xUk5AV4Fku6g&expires=1747430024",
        "referer": "https://stylisheleg4nt.com",
        "origin": "https://stylisheleg4nt.com"
    },
    {
        "name": "PTV Sports",
        "id": "ptvpk",
        "logo": "https://cdn.jsdelivr.net/gh/HelloPeopleTv4you/tv-logo@refs/heads/main/crichd2-runded/20-by-xfireflix.png",
        "link": "https://m1.merichunidya.com:999/hls/ptvpk.m3u8?md5=1vJ9EUaRke4nR3FRwdECJw&expires=1747430025",
        "referer": "https://stylisheleg4nt.com",
        "origin": "https://stylisheleg4nt.com"
    },
    {
        "name": "Willow HD",
        "id": "willowusa",
        "logo": "https://cdn.jsdelivr.net/gh/HelloPeopleTv4you/tv-logo@refs/heads/main/crichd2-runded/38-by-xfireflix.png",
        "link": "https://m1.merichunidya.com:999/hls/willowusa.m3u8?md5=x4HPZVVjsJw05ktQ0sd45Q&expires=1747430025",
        "referer": "https://stylisheleg4nt.com",
        "origin": "https://stylisheleg4nt.com"
    },
    {
        "name": "Willow HD 2",
        "id": "willowextra",
        "logo": "https://cdn.jsdelivr.net/gh/HelloPeopleTv4you/tv-logo@refs/heads/main/crichd2-runded/8-by-xfireflix.png",
        "link": "https://off1.gogohaalmal.com:1686/hls/willowextra.m3u8?md5=kuiE-qMBuV7YkKJ0uqpczQ&expires=1747430025",
        "referer": "https://stylisheleg4nt.com",
        "origin": "https://stylisheleg4nt.com"
    },
    {
        "name": "Ten Sports",
        "id": "tenspk",
        "logo": "https://cdn.jsdelivr.net/gh/HelloPeopleTv4you/tv-logo@refs/heads/main/crichd2-runded/10-by-xfireflix.png",
        "link": "https://off1.gogohaalmal.com:1686/hls/tenspk.m3u8?md5=co9ClIdS3UtMThYT0Qanew&expires=1747430025",
        "referer": "https://stylisheleg4nt.com",
        "origin": "https://stylisheleg4nt.com"
    },
    {
        "name": "A Sports HD",
        "id": "asportshd",
        "logo": "https://cdn.jsdelivr.net/gh/HelloPeopleTv4you/tv-logo@refs/heads/main/crichd2-runded/12-by-xfireflix.png",
        "link": "https://m1.merichunidya.com:999/hls/asportshd.m3u8?md5=075A_pNmVrR9tOc2w2UuCw&expires=1747430025",
        "referer": "https://stylisheleg4nt.com",
        "origin": "https://stylisheleg4nt.com"
    },
    {
        "name": "Sky Sports Cricket",
        "id": "skyscric",
        "logo": "https://cdn.jsdelivr.net/gh/HelloPeopleTv4you/tv-logo@refs/heads/main/crichd2-runded/9-by-xfireflix.png",
        "link": "https://m4.merichunidya.com:999/hls/skyscric.m3u8?md5=XpBmTY5GtszhftP_euEE9Q&expires=1747430026",
        "referer": "https://stylisheleg4nt.com",
        "origin": "https://stylisheleg4nt.com"
    },
    {
        "name": "Sky Sports Main Event",
        "logo": "https://cdn.jsdelivr.net/gh/HelloPeopleTv4you/tv-logo@refs/heads/main/crichd2-runded/18-by-xfireflix.png",
        "error": "Token not found or failed to fetch."
    },
    {
        "name": "TNT 1",
        "id": "bbtsp1",
        "logo": "https://cdn.jsdelivr.net/gh/HelloPeopleTv4you/tv-logo@refs/heads/main/crichd2-runded/tnt.png",
        "link": "https://m2.merichunidya.com:999/hls/bbtsp1.m3u8?md5=IZ-U1m7N293qL5A81tzgBA&expires=1747430026",
        "referer": "https://stylisheleg4nt.com",
        "origin": "https://stylisheleg4nt.com"
    },
    {
        "name": "TNT 2",
        "id": "bbtsp2",
        "logo": "https://cdn.jsdelivr.net/gh/HelloPeopleTv4you/tv-logo@refs/heads/main/crichd2-runded/tnt.png",
        "link": "https://off1.gogohaalmal.com:1686/hls/bbtsp2.m3u8?md5=VpfjF_nYnBKkxVWL5GQb-A&expires=1747430026",
        "referer": "https://stylisheleg4nt.com",
        "origin": "https://stylisheleg4nt.com"
    },
    {
        "name": "TNT 3",
        "logo": "https://cdn.jsdelivr.net/gh/HelloPeopleTv4you/tv-logo@refs/heads/main/crichd2-runded/tnt.png",
        "error": "Token not found or failed to fetch."
    },
    {
        "name": "TNT 4",
        "logo": "https://cdn.jsdelivr.net/gh/HelloPeopleTv4you/tv-logo@refs/heads/main/crichd2-runded/tnt.png",
        "error": "Token not found or failed to fetch."
    },
    {
        "name": "Sky Sports 1",
        "id": "sky1nz",
        "logo": "https://cdn.jsdelivr.net/gh/HelloPeopleTv4you/tv-logo@refs/heads/main/crichd2-runded/56-by-xfireflix.png",
        "link": "https://m2.merichunidya.com:999/hls/sky1nz.m3u8?md5=CznQ-gi_PM-YayEbfsC6yw&expires=1747430027",
        "referer": "https://stylisheleg4nt.com",
        "origin": "https://stylisheleg4nt.com"
    },
    {
        "name": "Sky Sports 2",
        "id": "sky2nz",
        "logo": "https://cdn.jsdelivr.net/gh/HelloPeopleTv4you/tv-logo@refs/heads/main/crichd2-runded/56-by-xfireflix.png",
        "link": "https://m1.merichunidya.com:999/hls/sky2nz.m3u8?md5=u8jDsQJeGitFd6AswvMYEg&expires=1747430027",
        "referer": "https://stylisheleg4nt.com",
        "origin": "https://stylisheleg4nt.com"
    },
    {
        "name": "Sky Sports 3",
        "id": "sky3nz",
        "logo": "https://cdn.jsdelivr.net/gh/HelloPeopleTv4you/tv-logo@refs/heads/main/crichd2-runded/56-by-xfireflix.png",
        "link": "https://m4.merichunidya.com:999/hls/sky3nz.m3u8?md5=GPckuJUzS4zCuShjQ6Q6aw&expires=1747430027",
        "referer": "https://stylisheleg4nt.com",
        "origin": "https://stylisheleg4nt.com"
    },
    {
        "name": "Sky Sports 4",
        "id": "sky4nz",
        "logo": "https://cdn.jsdelivr.net/gh/HelloPeopleTv4you/tv-logo@refs/heads/main/crichd2-runded/56-by-xfireflix.png",
        "link": "https://m2.merichunidya.com:999/hls/sky4nz.m3u8?md5=GJL7CUQZLZm9i0zbgI1q4g&expires=1747430028",
        "referer": "https://stylisheleg4nt.com",
        "origin": "https://stylisheleg4nt.com"
    },
    {
        "name": "Sky Sports 5",
        "id": "sky5nz",
        "logo": "https://cdn.jsdelivr.net/gh/HelloPeopleTv4you/tv-logo@refs/heads/main/crichd2-runded/56-by-xfireflix.png",
        "link": "https://m4.merichunidya.com:999/hls/sky5nz.m3u8?md5=t0Cl5C2RIAmSkX-efD96LQ&expires=1747430028",
        "referer": "https://stylisheleg4nt.com",
        "origin": "https://stylisheleg4nt.com"
    },
    {
        "name": "Sky Sports 6",
        "id": "sky6nz",
        "logo": "https://cdn.jsdelivr.net/gh/HelloPeopleTv4you/tv-logo@refs/heads/main/crichd2-runded/56-by-xfireflix.png",
        "link": "https://off1.gogohaalmal.com:1686/hls/sky6nz.m3u8?md5=Gyr_XLP04dCk0-nLJRNpcQ&expires=1747430028",
        "referer": "https://stylisheleg4nt.com",
        "origin": "https://stylisheleg4nt.com"
    },
    {
        "name": "Sky Sports 7",
        "id": "sky7nz",
        "logo": "https://cdn.jsdelivr.net/gh/HelloPeopleTv4you/tv-logo@refs/heads/main/crichd2-runded/56-by-xfireflix.png",
        "link": "https://off1.gogohaalmal.com:1686/hls/sky7nz.m3u8?md5=JZiUVf9NcytJLs6oTc12Rg&expires=1747430028",
        "referer": "https://stylisheleg4nt.com",
        "origin": "https://stylisheleg4nt.com"
    },
    {
        "name": "Sky Sports 8",
        "id": "sky8nz",
        "logo": "https://cdn.jsdelivr.net/gh/HelloPeopleTv4you/tv-logo@refs/heads/main/crichd2-runded/56-by-xfireflix.png",
        "link": "https://m2.merichunidya.com:999/hls/sky8nz.m3u8?md5=LgFgfEhmH5MmtJNTMdjWxA&expires=1747430028",
        "referer": "https://stylisheleg4nt.com",
        "origin": "https://stylisheleg4nt.com"
    },
    {
        "name": "Sky Sports 9",
        "id": "sky9nz",
        "logo": "https://cdn.jsdelivr.net/gh/HelloPeopleTv4you/tv-logo@refs/heads/main/crichd2-runded/56-by-xfireflix.png",
        "link": "https://m1.merichunidya.com:999/hls/sky9nz.m3u8?md5=OA2ttLl2V0IiemNYEi3knQ&expires=1747430029",
        "referer": "https://stylisheleg4nt.com",
        "origin": "https://stylisheleg4nt.com"
    },
    {
        "name": "Sky Cinema",
        "logo": "https://cdn.jsdelivr.net/gh/HelloPeopleTv4you/tv-logo@refs/heads/main/crichd2-runded/skycinema.png",
        "error": "Token not found or failed to fetch."
    },
    {
        "name": "Sky Sports Action",
        "id": "skysact",
        "logo": "https://cdn.jsdelivr.net/gh/HelloPeopleTv4you/tv-logo@refs/heads/main/crichd2-runded/1745007829332.png",
        "link": "https://m2.merichunidya.com:999/hls/skysact.m3u8?md5=5yuV37m15-wWLWNBehMpig&expires=1747430029",
        "referer": "https://stylisheleg4nt.com",
        "origin": "https://stylisheleg4nt.com"
    },
    {
        "name": "Sky Sports Golf",
        "id": "skysgol",
        "logo": "https://cdn.jsdelivr.net/gh/HelloPeopleTv4you/tv-logo@refs/heads/main/crichd2-runded/1745008055327.png",
        "link": "https://m1.merichunidya.com:999/hls/skysgol.m3u8?md5=f9sDQXPqBk3boohU7h659A&expires=1747430029",
        "referer": "https://stylisheleg4nt.com",
        "origin": "https://stylisheleg4nt.com"
    },
    {
        "name": "Sky Sports Premier League",
        "id": "skysprem",
        "logo": "https://cdn.jsdelivr.net/gh/HelloPeopleTv4you/tv-logo@refs/heads/main/crichd2-runded/43-by-xfireflix.png",
        "link": "https://m2.merichunidya.com:999/hls/skysprem.m3u8?md5=pNC3QO0OvBw-m7dIUraA4Q&expires=1747430029",
        "referer": "https://stylisheleg4nt.com",
        "origin": "https://stylisheleg4nt.com"
    },
    {
        "name": "Sky Sports Football",
        "logo": "https://cdn.jsdelivr.net/gh/HelloPeopleTv4you/tv-logo@refs/heads/main/crichd2-runded/44-by-xfireflix.png",
        "error": "Token not found or failed to fetch."
    },
    {
        "name": "Sky Sports Plus",
        "id": "skysare",
        "logo": "https://cdn.jsdelivr.net/gh/HelloPeopleTv4you/tv-logo@refs/heads/main/crichd2-runded/1745008347584.png",
        "link": "https://m1.merichunidya.com:999/hls/skysare.m3u8?md5=OlUgOqw3ibQYbbD58kwldg&expires=1747430030",
        "referer": "https://stylisheleg4nt.com",
        "origin": "https://stylisheleg4nt.com"
    },
    {
        "name": "Sky Sports F1",
        "logo": "https://cdn.jsdelivr.net/gh/HelloPeopleTv4you/tv-logo@refs/heads/main/crichd2-runded/1745008468637.png",
        "error": "Token not found or failed to fetch."
    },
    {
        "name": "LaLiGA",
        "id": "laligauk",
        "logo": "https://cdn.jsdelivr.net/gh/HelloPeopleTv4you/tv-logo@refs/heads/main/crichd2-runded/19-by-xfireflix.png",
        "link": "https://m3.merichunidya.com:999/hls/laligauk.m3u8?md5=BcW-qd02TYtqzstbAdWIQA&expires=1747430030",
        "referer": "https://stylisheleg4nt.com",
        "origin": "https://stylisheleg4nt.com"
    },
    {
        "name": "Premier Sports 1",
        "id": "premieruk",
        "logo": "https://cdn.jsdelivr.net/gh/HelloPeopleTv4you/tv-logo@refs/heads/main/crichd2-runded/31-by-xfireflix.png",
        "link": "https://m1.merichunidya.com:999/hls/premieruk.m3u8?md5=xUgpEkczKRu__Q9R3yX1ig&expires=1747430030",
        "referer": "https://stylisheleg4nt.com",
        "origin": "https://stylisheleg4nt.com"
    },
    {
        "name": "Premier Sports 2",
        "id": "hdchnl2",
        "logo": "https://cdn.jsdelivr.net/gh/HelloPeopleTv4you/tv-logo@refs/heads/main/crichd2-runded/31-by-xfireflix.png",
        "link": "https://m4.merichunidya.com:999/hls/hdchnl2.m3u8?md5=nqobOBB3XDo0k61Qy502pw&expires=1747430031",
        "referer": "https://stylisheleg4nt.com",
        "origin": "https://stylisheleg4nt.com"
    },
    {
        "name": "Super Football",
        "id": "superfotball",
        "logo": "https://cdn.jsdelivr.net/gh/HelloPeopleTv4you/tv-logo@refs/heads/main/crichd2-runded/34-by-xfireflix.png",
        "link": "https://off1.gogohaalmal.com:1686/hls/superfotball.m3u8?md5=q-kNb6559Rt0527vNt65rQ&expires=1747430031",
        "referer": "https://stylisheleg4nt.com",
        "origin": "https://stylisheleg4nt.com"
    },
    {
        "name": "Super Premier League",
        "id": "superpremier",
        "logo": "https://cdn.jsdelivr.net/gh/HelloPeopleTv4you/tv-logo@refs/heads/main/crichd2-runded/1745008781606.png",
        "link": "https://m1.merichunidya.com:999/hls/superpremier.m3u8?md5=UBaNE3-Ad5bl1VXhQOY1Yw&expires=1747430031",
        "referer": "https://stylisheleg4nt.com",
        "origin": "https://stylisheleg4nt.com"
    },
    {
        "name": "Astro Cricket",
        "id": "fox501",
        "logo": "https://cdn.jsdelivr.net/gh/HelloPeopleTv4you/tv-logo@refs/heads/main/crichd2-runded/1745008895589.png",
        "link": "https://m2.merichunidya.com:999/hls/fox501.m3u8?md5=lB_GCfrLGTRh1YaX0yFm2A&expires=1747430031",
        "referer": "https://stylisheleg4nt.com",
        "origin": "https://stylisheleg4nt.com"
    },
    {
        "name": "ESPN 1",
        "logo": "https://cdn.jsdelivr.net/gh/HelloPeopleTv4you/tv-logo@refs/heads/main/crichd2-runded/17-by-xfireflix.png",
        "error": "Token not found or failed to fetch."
    },
    {
        "name": "ESPN 2",
        "id": "espn2",
        "logo": "https://cdn.jsdelivr.net/gh/HelloPeopleTv4you/tv-logo@refs/heads/main/crichd2-runded/17-by-xfireflix.png",
        "link": "https://m4.merichunidya.com:999/hls/espn2.m3u8?md5=VmAe_XnDgESEGK6nbzFAxg&expires=1747430031",
        "referer": "https://stylisheleg4nt.com",
        "origin": "https://stylisheleg4nt.com"
    },
    {
        "name": "Sky Sports Arena",
        "id": "skysare",
        "logo": "https://cdn.jsdelivr.net/gh/HelloPeopleTv4you/tv-logo@refs/heads/main/crichd2-runded/1745007829327.png",
        "link": "https://m4.merichunidya.com:999/hls/skysare.m3u8?md5=L2duoFW9W2kpeIVRHWFiwg&expires=1747430032",
        "referer": "https://stylisheleg4nt.com",
        "origin": "https://stylisheleg4nt.com"
    },
    {
        "name": "Sky Sports Mix",
        "id": "skysmixx",
        "logo": "https://cdn.jsdelivr.net/gh/HelloPeopleTv4you/tv-logo@refs/heads/main/crichd2-runded/13-by-xfireflix.png",
        "link": "https://m2.merichunidya.com:999/hls/skysmixx.m3u8?md5=IwjH4UHvSKKAH3Y7m6Wk9g&expires=1747430032",
        "referer": "https://stylisheleg4nt.com",
        "origin": "https://stylisheleg4nt.com"
    },
    {
        "name": "Sky Sports Tennis",
        "id": "skystennis",
        "logo": "https://cdn.jsdelivr.net/gh/HelloPeopleTv4you/tv-logo@refs/heads/main/crichd2-runded/1745009085794.png",
        "link": "https://m2.merichunidya.com:999/hls/skystennis.m3u8?md5=BqivI66FR2qaA-HXE-qUfQ&expires=1747430032",
        "referer": "https://stylisheleg4nt.com",
        "origin": "https://stylisheleg4nt.com"
    },
    {
        "name": "Fox Cricket 501 HD",
        "id": "fox501",
        "logo": "https://cdn.jsdelivr.net/gh/HelloPeopleTv4you/tv-logo@refs/heads/main/crichd2-runded/6-by-xfireflix.png",
        "link": "https://m2.merichunidya.com:999/hls/fox501.m3u8?md5=udahXHumvvTaHLQQ0d5gYw&expires=1747430032",
        "referer": "https://stylisheleg4nt.com",
        "origin": "https://stylisheleg4nt.com"
    }
]